setup.cfg
setup.py
lmi/__init__.py
lmi/scripts/__init__.py
lmi/scripts/realmd/__init__.py
lmi/scripts/realmd/cmd.py
openlmi_scripts_realmd.egg-info/PKG-INFO
openlmi_scripts_realmd.egg-info/SOURCES.txt
openlmi_scripts_realmd.egg-info/dependency_links.txt
openlmi_scripts_realmd.egg-info/entry_points.txt
openlmi_scripts_realmd.egg-info/namespace_packages.txt
openlmi_scripts_realmd.egg-info/requires.txt
openlmi_scripts_realmd.egg-info/top_level.txt