Metadata-Version: 1.1
Name: openlmi-scripts-realmd
Version: 0.4.0
Summary: This command allows for basic management of the system Active Directory or Kerberos domain membership.
Home-page: https://github.com/openlmi/openlmi-realmd
Author: Tomas Smetana
Author-email: tsmetana@redhat.com
License: BSD
Download-URL: https://github.com/openlmi/openlmi-realmd/tarball/master
Platform: Any
Classifier: License :: OSI Approved :: BSD License
Classifier: Operating System :: POSIX :: Linux
Classifier: Topic :: System :: Systems Administration
Classifier: Programming Language :: Python
Classifier: Programming Language :: Python :: 2
Classifier: Programming Language :: Python :: 2.7
Classifier: Intended Audience :: Developers
Classifier: Environment :: Console
